binpolar/__init__.py
binpolar/polarity_detector.py
binpolar/tokenizer/special_tokens_map.json
binpolar/tokenizer/tokenizer_config.json
binpolar/tokenizer/vocab.txt
binpolar-1.3.dist-info/METADATA
binpolar-1.3.dist-info/WHEEL
binpolar-1.3.dist-info/top_level.txt
binpolar-1.3.dist-info/RECORD
