Metadata-Version: 2.1
Name: binpolar
Version: 1.3
Summary: Binary polarity detection
Author: Joyce Lee
Author-email: <leejoy1610@gmail.com>
Keywords: python,text,polarity
Classifier: Development Status :: 1 - Planning
Classifier: Intended Audience :: Developers
Classifier: Programming Language :: Python :: 3
Classifier: Operating System :: Unix
Classifier: Operating System :: MacOS :: MacOS X
Classifier: Operating System :: Microsoft :: Windows
Requires-Dist: transformers
Requires-Dist: huggingface-hub
